{
  "display": {
    "icon": {
      "id": "minecraft:rabbit_foot"
    },
    "title": {
      "translate": "statues.advancement.facade.speedrun.title"
    },
    "description": {
      "translate": "statues.advancement.facade.speedrun.description"
    },
    "frame": "challenge",
    "show_toast": true,
    "announce_to_chat": true,
    "hidden": false
  },
  "parent": "statues:game/maps/facade/win_as_survivor",
  "criteria": {
    "speedrun": {
      "trigger": "minecraft:impossible"
    }
  },
  "requirements": [
    [
      "speedrun"
    ]
  ]
}